smmc/__init__.py
smmc-0.1.5.dist-info/METADATA
smmc-0.1.5.dist-info/WHEEL
smmc-0.1.5.dist-info/top_level.txt
smmc-0.1.5.dist-info/RECORD
