Metadata-Version: 2.1
Name: smmc
Version: 0.1.5
Summary: ATLAS - Scanner Manager Message Coder
Home-page: UNKNOWN
Author: Robin Herrmann
Author-email: robin.herrmann@mgm-sp.com
License: GNU GPLv3
Platform: Linux
Requires-Dist: pybase64
